MANIFEST.in
README.rst
setup.cfg
setup.py
versioneer.py
mpg/__init__.py
mpg/_version.py
mpg/generator.py
mpg/main.py
mpg/test.py
mpg/util.py
mpg.egg-info/PKG-INFO
mpg.egg-info/SOURCES.txt
mpg.egg-info/dependency_links.txt
mpg.egg-info/entry_points.txt
mpg.egg-info/requires.txt
mpg.egg-info/top_level.txt