Metadata-Version: 1.1
Name: mpg
Version: 0.2.1
Summary: MPG: Markov Process Generator of DNA sequences
Home-page: https://github.com/kdmurray91/mpg
Author: Kevin Murray
Author-email: kdmfoss@gmail.com
License: UNKNOWN
Keywords: bioinformatics,Next-gen Sequencing
Platform: UNKNOWN
Classifier: Programming Language :: Python
Classifier: Programming Language :: Python :: 3
Classifier: Development Status :: 3 - Alpha
Classifier: Environment :: Console
Classifier: Intended Audience :: Developers
Classifier: Operating System :: OS Independent
Classifier: Topic :: Software Development :: Libraries :: Python Modules
Classifier: Topic :: Scientific/Engineering :: Bio-Informatics
Classifier: License :: OSI Approved :: MIT License
